[
  {
    "name": "Mariano Andújar",
    "goals": 0
  },
  {
    "name": "Nahuel Guzmán",
    "goals": 0
  },
  {
    "name": "Sergio Romero",
    "goals": 0
  },
  {
    "name": "Ramiro Funes Mori",
    "goals": 0
  },
  {
    "name": "Jonatan Ramón Maidana",
    "goals": 0
  },
  {
    "name": "Gabriel Iván Mercado",
    "goals": 0
  },
  {
    "name": "Nicolás Otamendi",
    "goals": 0
  },
  {
    "name": "Marcos Rojo",
    "goals": 0
  },
  {
    "name": "Victor Cuesta",
    "goals": 0
  },
  {
    "name": "Facundo Roncaglia",
    "goals": 0
  },
  {
    "name": "Ever Banega",
    "goals": 0
  },
  {
    "name": "Lucas Biglia",
    "goals": 0
  },
  {
    "name": "Augusto Fernández",
    "goals": 0
  },
  {
    "name": "Matías Kranevitter",
    "goals": 0
  },
  {
    "name": "Erik Lamela",
    "goals": 0
  },
  {
    "name": "Javier Mascherano",
    "goals": 0
  },
  {
    "name": "Javier Pastore",
    "goals": 0
  },
  {
    "name": "Sergio Agüero",
    "goals": 0
  },
  {
    "name": "Ángel Di María",
    "goals": 0
  },
  {
    "name": "Gonzalo Higuaín",
    "goals": 0
  },
  {
    "name": "Ezequiel Lavezzi",
    "goals": 0
  },
  {
    "name": "Lionel Messi",
    "goals": 0
  },
  {
    "name": "Nicolás Gaitán",
    "goals": 0
  }
]
